statplotastro/__init__.py
statplotastro-0.0.0.dist-info/METADATA
statplotastro-0.0.0.dist-info/WHEEL
statplotastro-0.0.0.dist-info/licenses/LICENSE
statplotastro-0.0.0.dist-info/RECORD
